{
	"name": "Cars",
	"properties": {
		"linkedServiceName": {
			"referenceName": "AzureBlobStorage_linkedserice",
			"type": "LinkedServiceReference"
		},
		"folder": {
			"name": "Rahul"
		},
		"annotations": [],
		"type": "DelimitedText",
		"typeProperties": {
			"location": {
				"type": "AzureBlobStorageLocation",
				"fileName": "employee.csv",
				"container": "containerahul"
			},
			"columnDelimiter": ",",
			"escapeChar": "\\",
			"firstRowAsHeader": true,
			"quoteChar": "\""
		},
		"schema": [
			{
				"name": "Empname",
				"type": "String"
			},
			{
				"name": "Did",
				"type": "String"
			}
		]
	},
	"type": "Microsoft.DataFactory/factories/datasets"
}