{
	"name": "schedule_trigger_",
	"properties": {
		"description": "daily basis trigger run",
		"annotations": [],
		"runtimeState": "Stopped",
		"pipelines": [
			{
				"pipelineReference": {
					"referenceName": "incremental_load_pipeline",
					"type": "PipelineReference"
				}
			}
		],
		"type": "ScheduleTrigger",
		"typeProperties": {
			"recurrence": {
				"frequency": "Day",
				"interval": 1,
				"startTime": "2022-01-08T08:11:00Z",
				"timeZone": "UTC",
				"schedule": {
					"minutes": [
						15
					],
					"hours": [
						10
					]
				}
			}
		}
	}
}